{
  "swagger": "2.0",
  "info": {
    "version": "2021-05-19T22:03:12Z",
    "title": "mrlSaveClassificationAPI"
  },
  "host": "vl0f6177xb.execute-api.us-west-2.amazonaws.com",
  "basePath": "/prod",
  "schemes": [
    "https"
  ],
  "paths": {
    "/save-classification": {
      "put": {
        "produces": [
          "application/json"
        ],
        "parameters": [
          {
            "name": "image",
            "in": "header",
            "required": false,
            "type": "string"
          },
          {
            "name": "class",
            "in": "header",
            "required": false,
            "type": "string"
          }
        ],
        "responses": {
          "200": {
            "description": "200 response",
            "schema": {
              "$ref": "#/definitions/Empty"
            },
            "headers": {
              "Access-Control-Allow-Origin": {
                "type": "string"
              }
            }
          }
        },
        "x-amazon-apigateway-integration": {
          "type": "aws_proxy",
          "responses": {
            "default": {
              "statusCode": "200",
              "responseParameters": {
                "method.response.header.Access-Control-Allow-Origin": "'*'"
              }
            }
          },
          "httpMethod": "POST",
          "uri": "arn:aws:apigateway:us-west-2:lambda:path/2015-03-31/functions/arn:aws:lambda:us-west-2:314359620323:function:mrl-saveClassification/invocations",
          "passthroughBehavior": "when_no_match",
          "contentHandling": "CONVERT_TO_TEXT"
        }
      },
      "options": {
        "consumes": [
          "application/json"
        ],
        "produces": [
          "application/json"
        ],
        "responses": {
          "200": {
            "description": "200 response",
            "schema": {
              "$ref": "#/definitions/Empty"
            },
            "headers": {
              "Access-Control-Allow-Origin": {
                "type": "string"
              },
              "Access-Control-Allow-Methods": {
                "type": "string"
              },
              "Access-Control-Allow-Headers": {
                "type": "string"
              }
            }
          }
        },
        "x-amazon-apigateway-integration": {
          "type": "mock",
          "responses": {
            "default": {
              "statusCode": "200",
              "responseParameters": {
                "method.response.header.Access-Control-Allow-Methods": "'OPTIONS,PUT'",
                "method.response.header.Access-Control-Allow-Headers": "'Content-Type,X-Amz-Date,Authorization,X-Api-Key,X-Amz-Security-Token'",
                "method.response.header.Access-Control-Allow-Origin": "'*'"
              }
            }
          },
          "requestTemplates": {
            "application/json": "{\"statusCode\": 200}"
          },
          "passthroughBehavior": "when_no_match"
        }
      }
    }
  },
  "definitions": {
    "Empty": {
      "type": "object",
      "title": "Empty Schema"
    }
  }
}